gradient_compression/__init__.py
gradient_compression/rp_compression.py
gradient_compression-0.0.2.dist-info/LICENSE
gradient_compression-0.0.2.dist-info/METADATA
gradient_compression-0.0.2.dist-info/WHEEL
gradient_compression-0.0.2.dist-info/top_level.txt
gradient_compression-0.0.2.dist-info/RECORD
